torch_cubic_spline_grids/__init__.py
torch_cubic_spline_grids/_base_cubic_grid.py
torch_cubic_spline_grids/_constants.py
torch_cubic_spline_grids/b_spline_grids.py
torch_cubic_spline_grids/catmull_rom_grids.py
torch_cubic_spline_grids/interpolate_grids.py
torch_cubic_spline_grids/interpolate_pieces.py
torch_cubic_spline_grids/pad_grids.py
torch_cubic_spline_grids/utils.py
torch_cubic_spline_grids-0.0.10.dist-info/METADATA
torch_cubic_spline_grids-0.0.10.dist-info/WHEEL
torch_cubic_spline_grids-0.0.10.dist-info/licenses/LICENSE
torch_cubic_spline_grids-0.0.10.dist-info/RECORD
