Metadata-Version: 2.4
Name: torch-cubic-spline-grids
Version: 0.0.10
Summary: Cubic spline interpolation on multidimensional grids in PyTorch
Project-URL: homepage, https://github.com/alisterburt/torch-cubic-spline-grids
Project-URL: repository, https://github.com/alisterburt/torch-cubic-spline-grids
Author: Alister Burt
Author-email: alisterburt@gmail.com
License: BSD 3-Clause License
License-File: LICENSE
Classifier: Development Status :: 3 - Alpha
Classifier: License :: OSI Approved :: BSD License
Classifier: Programming Language :: Python :: 3
Classifier: Programming Language :: Python :: 3.9
Classifier: Programming Language :: Python :: 3.10
Classifier: Programming Language :: Python :: 3.11
Classifier: Programming Language :: Python :: 3.12
Classifier: Programming Language :: Python :: 3.13
Requires-Python: >=3.9
Requires-Dist: einops
Requires-Dist: numpy
Requires-Dist: torch
Requires-Dist: typing-extensions
Provides-Extra: dev
Requires-Dist: ipython; extra == 'dev'
Requires-Dist: mypy; extra == 'dev'
Requires-Dist: pdbpp; extra == 'dev'
Requires-Dist: pre-commit; extra == 'dev'
Requires-Dist: pytest; extra == 'dev'
Requires-Dist: pytest-cov; extra == 'dev'
Requires-Dist: rich; extra == 'dev'
Requires-Dist: ruff; extra == 'dev'
Provides-Extra: test
Requires-Dist: pytest-cov; extra == 'test'
Requires-Dist: pytest>=6.0; extra == 'test'
